ont_guppy_duplex_pipeline/__init__.py
ont_guppy_duplex_pipeline/candidate_filtering.py
ont_guppy_duplex_pipeline/channel_neighbours.py
ont_guppy_duplex_pipeline/guppy_duplex.py
ont_guppy_duplex_pipeline-1.0.3.dist-info/METADATA
ont_guppy_duplex_pipeline-1.0.3.dist-info/WHEEL
ont_guppy_duplex_pipeline-1.0.3.dist-info/entry_points.txt
ont_guppy_duplex_pipeline-1.0.3.dist-info/top_level.txt
ont_guppy_duplex_pipeline-1.0.3.dist-info/RECORD
