Metadata-Version: 2.1
Name: ont-guppy-duplex-pipeline
Version: 1.0.3
Summary: Oxford Nanopore Technologies duplex pipeline scripts for guppy
Home-page: https://nanoporetech.com
Author: Oxford Nanopore Technologies plc
License: MPL 2.0
Keywords: guppy duplex basecalling nanopore
Classifier: Development Status :: 5 - Production/Stable
Classifier: Environment :: Console
Classifier: Intended Audience :: Developers
Classifier: Intended Audience :: Science/Research
Classifier: License :: OSI Approved :: Mozilla Public License 2.0 (MPL 2.0)
Classifier: Natural Language :: English
Classifier: Operating System :: Microsoft :: Windows
Classifier: Operating System :: POSIX :: Linux
Classifier: Operating System :: MacOS
Classifier: Programming Language :: Python :: 3 :: Only
Classifier: Topic :: Scientific/Engineering :: Bio-Informatics
Requires-Python: >=3.6
Requires-Dist: parasail (<1.3)
Requires-Dist: pandas
Requires-Dist: pyfastx
